key_driver_analysis/__init__.py
key_driver_analysis/kda.py
key_driver_analysis/version.py
key_driver_analysis-0.1.2.dist-info/METADATA
key_driver_analysis-0.1.2.dist-info/WHEEL
key_driver_analysis-0.1.2.dist-info/top_level.txt
key_driver_analysis-0.1.2.dist-info/RECORD
