Metadata-Version: 2.1
Name: key-driver-analysis
Version: 0.1.2
Summary: Key Driver Analysis
Home-page: https://github.com/bnriiitb/key-driver-analysis
Author: Nagaraju Budigam
Author-email: nagaraju.iith@gmail.com
License: MIT
Platform: UNKNOWN
Classifier: License :: OSI Approved :: MIT License
Classifier: Programming Language :: Python :: 3
Classifier: Programming Language :: Python :: 3.7
Classifier: Programming Language :: Python :: 3.8
Requires-Dist: numpy (>=1.21.3)
Requires-Dist: pandas (>=1.3.4)
Requires-Dist: scikit-learn (>=1.0.1)
Requires-Dist: setuptools (>=58.0.4)
